skoopy/__init__.py
skoopy/controller.py
skoopy/registry.py
skoopy/scanner.py
skoopy/transport.py
skoopy-0.1.0.dev1.dist-info/DESCRIPTION.rst
skoopy-0.1.0.dev1.dist-info/LICENSE.txt
skoopy-0.1.0.dev1.dist-info/METADATA
skoopy-0.1.0.dev1.dist-info/RECORD
skoopy-0.1.0.dev1.dist-info/WHEEL
skoopy-0.1.0.dev1.dist-info/entry_points.txt
skoopy-0.1.0.dev1.dist-info/metadata.json
skoopy-0.1.0.dev1.dist-info/top_level.txt
