Metadata-Version: 2.0
Name: skoopy
Version: 0.1.0.dev1
Summary: Skoobot control module
Home-page: https://github.com/rablack/skoopy
Author: Robert Black
License: MIT
Platform: UNKNOWN
Requires-Python: >=3
Requires-Dist: bluepy
Requires-Dist: uuid
